[
 {
   "Target": "SAO65921",
   "Type": "Star",
   "J mag": "4.6",
   "Sunset Date(s)": "20180523<br />20180524",
   "Seeing (AO)": "NR<br />1.3\"",
   "Filters": "Open and Open <br />Open and Open",
   "Time Windows": "01:25-4:00<br />00:25-01:03",
   "Nearby Laser Cals": "1:00<br />00:11",
   "Important Notes": "",
   "Number of Dithers": "3<br />NR",
   "AO Saved State": "20180524_tl_d",
   "BIN File Range": "1527150300 to 1527159659<br />1527233100 to 1527235439",
   "Simbad Webpage": "<a href = 'http://simbad.u-strasbg.fr/simbad/sim-id?Ident=HIP+84606' target='_blank'> Click Here! </a>"
 },
 {
   "Target": "SAO44531",
   "Type": "Binary Star System",
   "J mag": "5.4",
   "Sunset Date(s)": "20180524,<br />20180527, <br />20180528,<br />20180529",
   "Seeing (AO)": "1.4\", <br />2.03\", <br />2\", 1.5\", 1.6\"<br />1.7\", 2\"<br />1.37\", >1.5\"",
   "Filters": "J Band Open; J Band 0.5,1.5.2,5 --<br />J Band Open and Open, --<br />J Band Open and Open, J Band <br />Closed OD Closed, J Band OD 0.5 --<br />J Band, Dark. J Band and OD Open<br />Y Band Open. Z Band and Closed.<br />J Band and Closed. J Band OD 0.5.",
   "Time Windows": "21:30-00:02<br />20:45-22:35<br />20:42-00:49<br />20:22-23:58<br />",
   "Nearby Laser Cals": "21:02 (1527220960 - 1527221375), 00:11 (1527232550 - 1527232550)<br />20:57<br />20:27, 20:55, 21:37, 23:56, 00:39<br />20:27, 22:19, 22:41<br />",
   "Important Notes": "",
   "Number of Dithers": "2<br />None<br />3<br />8",
   "AO Saved State": "",
   "BIN File Range": "1527222599 to 1527231660<br />1527479324 to 1527485759<br />1527566146 to 1527580199<br />1527651051 to 1527663539",
   "Simbad Webpage": "<a href = 'http://simbad.u-strasbg.fr/simbad/sim-id?Ident=19+CVn' target='_blank'> Click Here! </a>"
 },
 {
   "Target": "Tau Boo",
   "Type": "Binary Star System",
   "J mag": "3.6",
   "Sunset Date(s)": "20180527<br />20180530",
   "Seeing (AO)": "2.71\"<br />1.2\", 1.24\", 1.65\"",
   "Filters": "J Band Open, OD Open, OD 0.5<br />J Band, OD 1.5. OD 0.5. OD 2.5. OD 1.5 and JD Open. OD 1.5.",
   "Time Windows": "22:44-23:57<br />21:55-01:58",
   "Nearby Laser Cals": "22:58<br />00:35",
   "Important Notes": "",
   "Number of Dithers": "NR",
   "AO Saved State": "",
   "BIN File Range": "1527487024 to 1527490679<br />1527742858 to 1527757234",
   "Simbad Webpage": "<a href = 'http://simbad.u-strasbg.fr/simbad/sim-id?Ident=*+tau+Boo' target='_blank'> Click Here! </a>"

 },
 {
   "Target": "Vega",
   "Type": "Variable Star",
   "J mag": "-0.18",
   "Sunset Date(s)": "20180527<br />20180528<br />20180530",
   "Seeing (AO)": "2.12\" --<br />~1.5\", 2.24\" --<br />~1.2\", 1.05\", 1.1\"1.81\"",
   "Filters": "J Band Open, OD 2.5, OD 1.5 --<br />J Band and OD 1.5<br />J Band, OD 2.5, OD 1.5. OD 2.5, OD 1.5",
   "Time Windows": "NR<br />04:20-04:55<br />02:00-03:22",
   "Nearby Laser Cals": "00:46<br />None<br />None",
   "Important Notes": "",
   "Number of Dithers": "",
   "AO Saved State": "",
   "BIN File Range": "NR<br />1527592800 to 1527594960<br />1527757200 to 1527762160",
   "Simbad Webpage": "<a href = 'http://simbad.u-strasbg.fr/simbad/sim-id?Ident=Vega' target='_blank'> Click Here! </a>"
 },
 {
   "Target": "Omega Her",
   "Type": "Variable Star",
   "J mag": "4.6",
   "Sunset Date(s)": "20180529",
   "Seeing (AO)": "1.41\"",
   "Filters": "J Band and OD 0.5. OD Open. OD 1.5; J Band, OD Open. OD 0.5. OD 1.5.",
   "Time Windows": "00:47-03:21",
   "Nearby Laser Cals": "00:57, 03:21",
   "Important Notes": "",
   "Number of Dithers": "",
   "AO Saved State": "",
   "BIN File Range": "1527666447 to 1527675719",
   "Simbad Webpage": "<a href = 'http://simbad.u-strasbg.fr/simbad/sim-id?protocol=html&Ident=Omega+Herculis&NbIdent=1&Radius=2&Radius.unit=arcmin&submit=submit+id' target='_blank'> Click Here! </a>"
 },
 {
   "Target": "SAO47913",
   "Type": "Star",
   "J mag": "5.8(V Mag)",
   "Sunset Date(s)": "20180529",
   "Seeing (AO)": "1.5\"",
   "Filters": "J Band OD 1.5., OD 0.5, OD Open.<br />OD Open and J Band.",
   "Time Windows": "3:32-5:22",
   "Nearby Laser Cals": "5:03",
   "Important Notes": "",
   "Number of Dithers": "1",
   "AO Saved State": "",
   "BIN File Range": "1527676320 to 1527682979",
   "Simbad Webpage": "<a href = 'http://simbad.u-strasbg.fr/simbad/sim-id?Ident=SAO%2047913' target='_blank'> Click Here! </a>"
 },
 {
   "Target": "HD114174",
   "Type": "Binary Star System",
   "J mag": "5.6",
   "Sunset Date(s)": "20180530",
   "Seeing (AO)": "1.6\"",
   "Filters": "J Band, OD 0.5, OD Open.",
   "Time Windows": "20:42-21:47",
   "Nearby Laser Cals": "20:54",
   "Important Notes": "",
   "Number of Dithers": "4",
   "AO Saved State": "",
   "BIN File Range": "1527738455 to 1527742079",
   "Simbad Webpage": "<a href = 'http://simbad.u-strasbg.fr/simbad/sim-id?Ident=%402106944&Name=HD%20114174&submit=submit' target='_blank'> Click Here! </a>"
 },
 {
   "Target": "White Light",
   "Type": "Not a Star (Calibration)",
   "J mag": "None",
   "Sunset Date(s)": "20180530",
   "Seeing (AO)": "1.81\"",
   "Filters": "J Band, OD 1.5, OD Open.",
   "Time Windows": "3:22-5:36",
   "Nearby Laser Cals": "5:17",
   "Important Notes": "Calibration Purposes",
   "Number of Dithers": "",
   "AO Saved State": "",
   "BIN File Range": "1527762120 to 1527770545",
   "Simbad Webpage": "None"
 }
]